{
  "timestamp": "2025-11-25T17:01:33Z",
  "data": [
    {
      "askSz": "0.84104",
      "baseVol": "8449.824256",
      "bidSz": "2.613782",
      "buyOne": "87152.95",
      "change": "-0.00175",
      "changeUtc": "-0.0129",
      "close": "87150.91",
      "high24h": "89212.7",
      "low24h": "86111.12",
      "openUtc0": "88283.43",
      "quoteVol": "740586344.752126",
      "sellOne": "87152.96",
      "symbol": "BTCUSDT",
      "ts": "1764090092967",
      "usdtVol": "740586344.7521256"
    },
    {
      "askSz": "1.1432",
      "baseVol": "81538.3643",
      "bidSz": "2.9925",
      "buyOne": "2930.59",
      "change": "0.02308",
      "changeUtc": "-0.00775",
      "close": "2930.5",
      "high24h": "2985.98",
      "low24h": "2856.31",
      "openUtc0": "2953.29",
      "quoteVol": "238156944.5258",
      "sellOne": "2930.6",
      "symbol": "ETHUSDT",
      "ts": "1764090092659",
      "usdtVol": "238156944.525709"
    },
    {
      "askSz": "48.5406",
      "baseVol": "614796.6991",
      "bidSz": "106.6077",
      "buyOne": "136.22",
      "change": "0.01763",
      "changeUtc": "-0.01604",
      "close": "136.21",
      "high24h": "139.81",
      "low24h": "133.13",
      "openUtc0": "138.43",
      "quoteVol": "84158534.0179",
      "sellOne": "136.23",
      "symbol": "SOLUSDT",
      "ts": "1764090092967",
      "usdtVol": "84158534.017893"
    },
    {
      "askSz": "15152.81",
      "baseVol": "12049690.54",
      "bidSz": "996.61",
      "buyOne": "0.2403",
      "change": "0.0152",
      "changeUtc": "0.00797",
      "close": "0.2404",
      "high24h": "0.241",
      "low24h": "0.2346",
      "openUtc0": "0.2385",
      "quoteVol": "2873167.21",
      "sellOne": "0.2404",
      "symbol": "PIUSDT",
      "ts": "1764090092698",
      "usdtVol": "2873167.204386"
    }
  ]
}
