{
  "timestamp": "2025-10-30T09:37:47Z",
  "data": [
    {
      "askSz": "0.733283",
      "baseVol": "4219.457169",
      "bidSz": "0.523626",
      "buyOne": "110223.73",
      "change": "-0.02369",
      "changeUtc": "0.00178",
      "close": "110223.73",
      "high24h": "113639.25",
      "low24h": "107935.99",
      "openUtc0": "110028.37",
      "quoteVol": "468115765.785151",
      "sellOne": "110223.74",
      "symbol": "BTCUSDT",
      "ts": "1761817067013",
      "usdtVol": "468115765.78515009"
    },
    {
      "askSz": "8.3913",
      "baseVol": "72074.7684",
      "bidSz": "0.142",
      "buyOne": "3897.9",
      "change": "-0.02439",
      "changeUtc": "-0.00143",
      "close": "3898",
      "high24h": "4030.4",
      "low24h": "3840",
      "openUtc0": "3903.58",
      "quoteVol": "283504258.7293",
      "sellOne": "3897.91",
      "symbol": "ETHUSDT",
      "ts": "1761817067014",
      "usdtVol": "283504258.729291"
    },
    {
      "askSz": "38.2217",
      "baseVol": "434987.1438",
      "bidSz": "70.981",
      "buyOne": "192.72",
      "change": "-0.00701",
      "changeUtc": "-0.00583",
      "close": "192.73",
      "high24h": "201.71",
      "low24h": "189.46",
      "openUtc0": "193.86",
      "quoteVol": "84901333.6788",
      "sellOne": "192.73",
      "symbol": "SOLUSDT",
      "ts": "1761817067014",
      "usdtVol": "84901333.678768"
    },
    {
      "askSz": "2749.07",
      "baseVol": "27180557.16",
      "bidSz": "244.62",
      "buyOne": "0.2593",
      "change": "-0.01928",
      "changeUtc": "0.00387",
      "close": "0.2594",
      "high24h": "0.286",
      "low24h": "0.2487",
      "openUtc0": "0.2584",
      "quoteVol": "7305027.93",
      "sellOne": "0.2594",
      "symbol": "PIUSDT",
      "ts": "1761817067064",
      "usdtVol": "7305027.929367"
    }
  ]
}
