{
  "timestamp": "2025-11-01T17:54:10Z",
  "data": [
    {
      "askSz": "3.00164",
      "baseVol": "2418.781332",
      "bidSz": "0.671505",
      "buyOne": "110235.43",
      "change": "0.00791",
      "changeUtc": "0.00569",
      "close": "110235.43",
      "high24h": "110562.34",
      "low24h": "108976.74",
      "openUtc0": "109611.22",
      "quoteVol": "266013056.049204",
      "sellOne": "110235.44",
      "symbol": "BTCUSDT",
      "ts": "1762019648425",
      "usdtVol": "266013056.04920363"
    },
    {
      "askSz": "8.1844",
      "baseVol": "35850.382",
      "bidSz": "2.3783",
      "buyOne": "3863.16",
      "change": "0.00822",
      "changeUtc": "0.00404",
      "close": "3863.16",
      "high24h": "3909.41",
      "low24h": "3808.84",
      "openUtc0": "3847.61",
      "quoteVol": "138572432.4263",
      "sellOne": "3863.17",
      "symbol": "ETHUSDT",
      "ts": "1762019648422",
      "usdtVol": "138572432.42626"
    },
    {
      "askSz": "134.5995",
      "baseVol": "166515.3091",
      "bidSz": "41.895",
      "buyOne": "185.07",
      "change": "-0.00371",
      "changeUtc": "-0.01159",
      "close": "185.08",
      "high24h": "189.11",
      "low24h": "183.84",
      "openUtc0": "187.25",
      "quoteVol": "31045911.9436",
      "sellOne": "185.08",
      "symbol": "SOLUSDT",
      "ts": "1762019648425",
      "usdtVol": "31045911.943576"
    },
    {
      "askSz": "587.5",
      "baseVol": "9270574.17",
      "bidSz": "1285.61",
      "buyOne": "0.2467",
      "change": "-0.00524",
      "changeUtc": "-0.01122",
      "close": "0.2468",
      "high24h": "0.2541",
      "low24h": "0.2443",
      "openUtc0": "0.2496",
      "quoteVol": "2311621.34",
      "sellOne": "0.2468",
      "symbol": "PIUSDT",
      "ts": "1762019648490",
      "usdtVol": "2311621.331019"
    }
  ]
}
