{
  "timestamp": "2025-11-28T07:32:26Z",
  "data": [
    {
      "askSz": "6.690956",
      "baseVol": "4141.48426",
      "bidSz": "0.338186",
      "buyOne": "91413.44",
      "change": "0.00044",
      "changeUtc": "0.00092",
      "close": "91413.76",
      "high24h": "91926.09",
      "low24h": "90444.24",
      "openUtc0": "91332.39",
      "quoteVol": "377805940.106743",
      "sellOne": "91413.45",
      "symbol": "BTCUSDT",
      "ts": "1764315145375",
      "usdtVol": "377805940.10674283"
    },
    {
      "askSz": "7.2661",
      "baseVol": "43001.3663",
      "bidSz": "2.3667",
      "buyOne": "3019.64",
      "change": "-0.00328",
      "changeUtc": "0.00144",
      "close": "3019.65",
      "high24h": "3045.02",
      "low24h": "2985.92",
      "openUtc0": "3015.32",
      "quoteVol": "129558057.7292",
      "sellOne": "3019.65",
      "symbol": "ETHUSDT",
      "ts": "1764315145376",
      "usdtVol": "129558057.729186"
    },
    {
      "askSz": "117.8664",
      "baseVol": "330069.8086",
      "bidSz": "67.9837",
      "buyOne": "139.83",
      "change": "-0.02666",
      "changeUtc": "-0.00696",
      "close": "139.84",
      "high24h": "144",
      "low24h": "138.58",
      "openUtc0": "140.82",
      "quoteVol": "46615467.5563",
      "sellOne": "139.84",
      "symbol": "SOLUSDT",
      "ts": "1764315145376",
      "usdtVol": "46615467.556259"
    },
    {
      "askSz": "5491.84",
      "baseVol": "24395142.29",
      "bidSz": "981.78",
      "buyOne": "0.259",
      "change": "0.02777",
      "changeUtc": "-0.04743",
      "close": "0.2591",
      "high24h": "0.284",
      "low24h": "0.2521",
      "openUtc0": "0.272",
      "quoteVol": "6529523.08",
      "sellOne": "0.2591",
      "symbol": "PIUSDT",
      "ts": "1764315145441",
      "usdtVol": "6529523.07549"
    }
  ]
}
