{
  "timestamp": "2025-11-24T14:41:04Z",
  "data": [
    {
      "askSz": "0.930731",
      "baseVol": "7624.648843",
      "bidSz": "0.882389",
      "buyOne": "85769.32",
      "change": "-0.01245",
      "changeUtc": "-0.01254",
      "close": "85769.32",
      "high24h": "88126.87",
      "low24h": "85692.63",
      "openUtc0": "86837.14",
      "quoteVol": "662293696.453363",
      "sellOne": "85769.33",
      "symbol": "BTCUSDT",
      "ts": "1763995262837",
      "usdtVol": "662293696.45336215"
    },
    {
      "askSz": "2.7179",
      "baseVol": "76482.6237",
      "bidSz": "0.0532",
      "buyOne": "2819.49",
      "change": "-0.00474",
      "changeUtc": "0.00571",
      "close": "2819.05",
      "high24h": "2885.54",
      "low24h": "2763.11",
      "openUtc0": "2802.61",
      "quoteVol": "215961924.5872",
      "sellOne": "2819.5",
      "symbol": "ETHUSDT",
      "ts": "1763995262837",
      "usdtVol": "215961924.58719"
    },
    {
      "askSz": "30.2892",
      "baseVol": "520971.5668",
      "bidSz": "19.7696",
      "buyOne": "129.78",
      "change": "-0.0106",
      "changeUtc": "-0.00551",
      "close": "129.79",
      "high24h": "134.41",
      "low24h": "128.43",
      "openUtc0": "130.58",
      "quoteVol": "68326959.1847",
      "sellOne": "129.79",
      "symbol": "SOLUSDT",
      "ts": "1763995262839",
      "usdtVol": "68326959.184623"
    },
    {
      "askSz": "24083.38",
      "baseVol": "9760237.1",
      "bidSz": "5210.96",
      "buyOne": "0.236",
      "change": "-0.03158",
      "changeUtc": "-0.01952",
      "close": "0.2361",
      "high24h": "0.2445",
      "low24h": "0.2356",
      "openUtc0": "0.2408",
      "quoteVol": "2350767.82",
      "sellOne": "0.2362",
      "symbol": "PIUSDT",
      "ts": "1763995262903",
      "usdtVol": "2350767.812836"
    }
  ]
}
