{
  "timestamp": "2025-10-29T10:16:48Z",
  "data": [
    {
      "askSz": "0.185643",
      "baseVol": "2737.029776",
      "bidSz": "3.293084",
      "buyOne": "112899.74",
      "change": "-0.01387",
      "changeUtc": "0.00003",
      "close": "112899.74",
      "high24h": "116089.5",
      "low24h": "112096.2",
      "openUtc0": "112896.38",
      "quoteVol": "311751831.51133",
      "sellOne": "112899.75",
      "symbol": "BTCUSDT",
      "ts": "1761733007974",
      "usdtVol": "311751831.51132902"
    },
    {
      "askSz": "3.8067",
      "baseVol": "174571.6036",
      "bidSz": "3.7186",
      "buyOne": "3994.97",
      "change": "-0.02925",
      "changeUtc": "0.00359",
      "close": "3994.31",
      "high24h": "4176",
      "low24h": "3932.74",
      "openUtc0": "3980.01",
      "quoteVol": "708090808.2981",
      "sellOne": "3994.98",
      "symbol": "ETHUSDT",
      "ts": "1761733008582",
      "usdtVol": "708090808.298045"
    },
    {
      "askSz": "2.2198",
      "baseVol": "323644.409",
      "bidSz": "56.738",
      "buyOne": "194.12",
      "change": "-0.03442",
      "changeUtc": "-0.00031",
      "close": "194.12",
      "high24h": "203.02",
      "low24h": "190.3",
      "openUtc0": "194.18",
      "quoteVol": "63741823.0608",
      "sellOne": "194.13",
      "symbol": "SOLUSDT",
      "ts": "1761733007976",
      "usdtVol": "63741823.06078"
    },
    {
      "askSz": "926.31",
      "baseVol": "30580645.57",
      "bidSz": "3041.66",
      "buyOne": "0.27",
      "change": "0.16631",
      "changeUtc": "0.06635",
      "close": "0.27",
      "high24h": "0.2715",
      "low24h": "0.2314",
      "openUtc0": "0.2532",
      "quoteVol": "7797407.91",
      "sellOne": "0.2701",
      "symbol": "PIUSDT",
      "ts": "1761733008022",
      "usdtVol": "7797407.903801"
    }
  ]
}
