{
  "timestamp": "2025-11-15T10:45:19Z",
  "data": [
    {
      "askSz": "3.777643",
      "baseVol": "6864.572703",
      "bidSz": "0.470853",
      "buyOne": "95990.33",
      "change": "-0.01246",
      "changeUtc": "0.01479",
      "close": "95990.34",
      "high24h": "97411.43",
      "low24h": "94003.5",
      "openUtc0": "94592",
      "quoteVol": "656944328.383002",
      "sellOne": "95990.34",
      "symbol": "BTCUSDT",
      "ts": "1763203518408",
      "usdtVol": "656944328.3830013"
    },
    {
      "askSz": "0.9052",
      "baseVol": "101941.8781",
      "bidSz": "5.0105",
      "buyOne": "3166",
      "change": "-0.00731",
      "changeUtc": "0.0172",
      "close": "3166.1",
      "high24h": "3257.39",
      "low24h": "3069.96",
      "openUtc0": "3112.55",
      "quoteVol": "321827721.2007",
      "sellOne": "3166.01",
      "symbol": "ETHUSDT",
      "ts": "1763203518408",
      "usdtVol": "321827721.200627"
    },
    {
      "askSz": "50.2063",
      "baseVol": "533103.3268",
      "bidSz": "19.8971",
      "buyOne": "141.24",
      "change": "-0.00877",
      "changeUtc": "0.01685",
      "close": "141.25",
      "high24h": "144.24",
      "low24h": "135.76",
      "openUtc0": "138.91",
      "quoteVol": "74943470.1771",
      "sellOne": "141.25",
      "symbol": "SOLUSDT",
      "ts": "1763203518410",
      "usdtVol": "74943470.177077"
    },
    {
      "askSz": "3523.85",
      "baseVol": "10456564.03",
      "bidSz": "7084.26",
      "buyOne": "0.2186",
      "change": "0.00784",
      "changeUtc": "0.01486",
      "close": "0.2186",
      "high24h": "0.2206",
      "low24h": "0.2102",
      "openUtc0": "0.2154",
      "quoteVol": "2255619.76",
      "sellOne": "0.2187",
      "symbol": "PIUSDT",
      "ts": "1763203518784",
      "usdtVol": "2255619.758513"
    }
  ]
}
