{
  "timestamp": "2025-11-15T08:57:55Z",
  "data": [
    {
      "askSz": "0.009133",
      "baseVol": "6939.059544",
      "bidSz": "3.070764",
      "buyOne": "95908.18",
      "change": "-0.01432",
      "changeUtc": "0.01391",
      "close": "95908.19",
      "high24h": "97549.67",
      "low24h": "94003.5",
      "openUtc0": "94592",
      "quoteVol": "664475347.160544",
      "sellOne": "95908.19",
      "symbol": "BTCUSDT",
      "ts": "1763197073721",
      "usdtVol": "664475347.16054353"
    },
    {
      "askSz": "3.4408",
      "baseVol": "105204.6668",
      "bidSz": "6.9943",
      "buyOne": "3143.66",
      "change": "-0.01948",
      "changeUtc": "0.01",
      "close": "3143.67",
      "high24h": "3257.39",
      "low24h": "3069.96",
      "openUtc0": "3112.55",
      "quoteVol": "332253223.0523",
      "sellOne": "3143.67",
      "symbol": "ETHUSDT",
      "ts": "1763197074313",
      "usdtVol": "332253223.052204"
    },
    {
      "askSz": "53.6861",
      "baseVol": "543224.7034",
      "bidSz": "0.01",
      "buyOne": "140.9",
      "change": "-0.01053",
      "changeUtc": "0.0144",
      "close": "140.91",
      "high24h": "144.24",
      "low24h": "135.76",
      "openUtc0": "138.91",
      "quoteVol": "76390696.1677",
      "sellOne": "140.91",
      "symbol": "SOLUSDT",
      "ts": "1763197073722",
      "usdtVol": "76390696.167645"
    },
    {
      "askSz": "43152.29",
      "baseVol": "10954053.68",
      "bidSz": "10898.82",
      "buyOne": "0.2176",
      "change": "0.00461",
      "changeUtc": "0.01114",
      "close": "0.2178",
      "high24h": "0.2206",
      "low24h": "0.2102",
      "openUtc0": "0.2154",
      "quoteVol": "2362400.15",
      "sellOne": "0.2178",
      "symbol": "PIUSDT",
      "ts": "1763197074360",
      "usdtVol": "2362400.14799"
    }
  ]
}
