{
  "timestamp": "2025-11-24T13:57:22Z",
  "data": [
    {
      "askSz": "2.492807",
      "baseVol": "7556.70306",
      "bidSz": "0.836601",
      "buyOne": "86250.01",
      "change": "-0.00748",
      "changeUtc": "-0.00676",
      "close": "86250.01",
      "high24h": "88126.87",
      "low24h": "85692.63",
      "openUtc0": "86837.14",
      "quoteVol": "656651179.119733",
      "sellOne": "86250.02",
      "symbol": "BTCUSDT",
      "ts": "1763992641301",
      "usdtVol": "656651179.11973296"
    },
    {
      "askSz": "4.2734",
      "baseVol": "75648.1728",
      "bidSz": "2.2592",
      "buyOne": "2819.85",
      "change": "-0.00833",
      "changeUtc": "0.00615",
      "close": "2819.86",
      "high24h": "2885.54",
      "low24h": "2763.11",
      "openUtc0": "2802.61",
      "quoteVol": "213674066.8429",
      "sellOne": "2819.86",
      "symbol": "ETHUSDT",
      "ts": "1763992641300",
      "usdtVol": "213674066.842887"
    },
    {
      "askSz": "34.5041",
      "baseVol": "498917.965",
      "bidSz": "133.9797",
      "buyOne": "129.96",
      "change": "-0.01164",
      "changeUtc": "-0.00475",
      "close": "129.96",
      "high24h": "134.41",
      "low24h": "128.43",
      "openUtc0": "130.58",
      "quoteVol": "65497499.3127",
      "sellOne": "129.97",
      "symbol": "SOLUSDT",
      "ts": "1763992641304",
      "usdtVol": "65497499.312677"
    },
    {
      "askSz": "3892.32",
      "baseVol": "9784785.71",
      "bidSz": "29332.49",
      "buyOne": "0.2379",
      "change": "-0.00916",
      "changeUtc": "-0.01163",
      "close": "0.238",
      "high24h": "0.2447",
      "low24h": "0.2376",
      "openUtc0": "0.2408",
      "quoteVol": "2359670.56",
      "sellOne": "0.238",
      "symbol": "PIUSDT",
      "ts": "1763992641045",
      "usdtVol": "2359670.550931"
    }
  ]
}
