{
  "timestamp": "2025-11-03T23:30:31Z",
  "data": [
    {
      "askSz": "0.08561",
      "baseVol": "5295.731969",
      "bidSz": "2.490064",
      "buyOne": "106432.99",
      "change": "-0.03446",
      "changeUtc": "-0.03731",
      "close": "106432.32",
      "high24h": "110760.8",
      "low24h": "105317.28",
      "openUtc0": "110552",
      "quoteVol": "569340445.38004",
      "sellOne": "106433",
      "symbol": "BTCUSDT",
      "ts": "1762212630960",
      "usdtVol": "569340445.38003997"
    },
    {
      "askSz": "5.3016",
      "baseVol": "106625.7344",
      "bidSz": "9.9219",
      "buyOne": "3591.85",
      "change": "-0.07335",
      "changeUtc": "-0.08057",
      "close": "3591.85",
      "high24h": "3916.1",
      "low24h": "3557.98",
      "openUtc0": "3906.6",
      "quoteVol": "394147091.2059",
      "sellOne": "3591.86",
      "symbol": "ETHUSDT",
      "ts": "1762212630958",
      "usdtVol": "394147091.2059"
    },
    {
      "askSz": "16.8572",
      "baseVol": "769810.5501",
      "bidSz": "34.8417",
      "buyOne": "165.62",
      "change": "-0.11233",
      "changeUtc": "-0.11768",
      "close": "165.63",
      "high24h": "189.07",
      "low24h": "163.22",
      "openUtc0": "187.72",
      "quoteVol": "132802565.9504",
      "sellOne": "165.63",
      "symbol": "SOLUSDT",
      "ts": "1762212630959",
      "usdtVol": "132802565.950368"
    },
    {
      "askSz": "113925.65",
      "baseVol": "21720546.93",
      "bidSz": "787.5",
      "buyOne": "0.2281",
      "change": "-0.0861",
      "changeUtc": "-0.08939",
      "close": "0.2282",
      "high24h": "0.251",
      "low24h": "0.221",
      "openUtc0": "0.2506",
      "quoteVol": "5074489.83",
      "sellOne": "0.2282",
      "symbol": "PIUSDT",
      "ts": "1762212630373",
      "usdtVol": "5074489.829918"
    }
  ]
}
