{
  "timestamp": "2025-11-03T19:12:01Z",
  "data": [
    {
      "askSz": "0.005771",
      "baseVol": "5095.85016",
      "bidSz": "1.638622",
      "buyOne": "106688.41",
      "change": "-0.03212",
      "changeUtc": "-0.03495",
      "close": "106688.41",
      "high24h": "110760.8",
      "low24h": "105317.28",
      "openUtc0": "110552",
      "quoteVol": "549517405.034543",
      "sellOne": "106688.42",
      "symbol": "BTCUSDT",
      "ts": "1762197120716",
      "usdtVol": "549517405.03454264"
    },
    {
      "askSz": "2.0504",
      "baseVol": "95371.8548",
      "bidSz": "7.0753",
      "buyOne": "3626.88",
      "change": "-0.06113",
      "changeUtc": "-0.0716",
      "close": "3626.88",
      "high24h": "3916.1",
      "low24h": "3564.1",
      "openUtc0": "3906.6",
      "quoteVol": "354713544.6219",
      "sellOne": "3626.89",
      "symbol": "ETHUSDT",
      "ts": "1762197120718",
      "usdtVol": "354713544.621819"
    },
    {
      "askSz": "31.9541",
      "baseVol": "678247.0281",
      "bidSz": "23.7676",
      "buyOne": "167.22",
      "change": "-0.09184",
      "changeUtc": "-0.10921",
      "close": "167.22",
      "high24h": "189.07",
      "low24h": "164.83",
      "openUtc0": "187.72",
      "quoteVol": "118227688.0629",
      "sellOne": "167.23",
      "symbol": "SOLUSDT",
      "ts": "1762197120718",
      "usdtVol": "118227688.062809"
    },
    {
      "askSz": "2727.83",
      "baseVol": "19228788.65",
      "bidSz": "4675.57",
      "buyOne": "0.227",
      "change": "-0.08982",
      "changeUtc": "-0.09417",
      "close": "0.227",
      "high24h": "0.2517",
      "low24h": "0.221",
      "openUtc0": "0.2506",
      "quoteVol": "4537806.21",
      "sellOne": "0.2271",
      "symbol": "PIUSDT",
      "ts": "1762197120760",
      "usdtVol": "4537806.209378"
    }
  ]
}
