{
  "timestamp": "2025-11-09T01:10:09Z",
  "data": [
    {
      "askSz": "0.279265",
      "baseVol": "2540.872882",
      "bidSz": "3.546166",
      "buyOne": "101995.26",
      "change": "-0.00895",
      "changeUtc": "-0.00319",
      "close": "101990.51",
      "high24h": "103339.75",
      "low24h": "101460",
      "openUtc0": "102313.92",
      "quoteVol": "259699784.345634",
      "sellOne": "101995.27",
      "symbol": "BTCUSDT",
      "ts": "1762650608210",
      "usdtVol": "259699784.34563335"
    },
    {
      "askSz": "1.8984",
      "baseVol": "63104.6859",
      "bidSz": "7.2989",
      "buyOne": "3397.15",
      "change": "-0.0111",
      "changeUtc": "-0.0014",
      "close": "3397.07",
      "high24h": "3487.78",
      "low24h": "3355.71",
      "openUtc0": "3401.56",
      "quoteVol": "215844961.0642",
      "sellOne": "3397.16",
      "symbol": "ETHUSDT",
      "ts": "1762650608210",
      "usdtVol": "215844961.064178"
    },
    {
      "askSz": "21.322",
      "baseVol": "227389.6636",
      "bidSz": "91.4664",
      "buyOne": "157.52",
      "change": "-0.02645",
      "changeUtc": "-0.00316",
      "close": "157.53",
      "high24h": "164.92",
      "low24h": "155.83",
      "openUtc0": "158.01",
      "quoteVol": "36294530.7199",
      "sellOne": "157.53",
      "symbol": "SOLUSDT",
      "ts": "1762650608212",
      "usdtVol": "36294530.719879"
    },
    {
      "askSz": "82600.42",
      "baseVol": "10706541.47",
      "bidSz": "6469.58",
      "buyOne": "0.2243",
      "change": "0.00089",
      "changeUtc": "-0.00708",
      "close": "0.2245",
      "high24h": "0.2286",
      "low24h": "0.2213",
      "openUtc0": "0.2261",
      "quoteVol": "2405382.03",
      "sellOne": "0.2245",
      "symbol": "PIUSDT",
      "ts": "1762650608888",
      "usdtVol": "2405382.022326"
    }
  ]
}
