{
  "timestamp": "2025-11-26T11:14:15Z",
  "data": [
    {
      "askSz": "0.15639",
      "baseVol": "6603.10703",
      "bidSz": "5.160453",
      "buyOne": "86979.93",
      "change": "-0.00545",
      "changeUtc": "-0.00441",
      "close": "86979.94",
      "high24h": "88228.24",
      "low24h": "86111.12",
      "openUtc0": "87365.51",
      "quoteVol": "576037302.004506",
      "sellOne": "86979.94",
      "symbol": "BTCUSDT",
      "ts": "1764155653983",
      "usdtVol": "576037302.00450558"
    },
    {
      "askSz": "1.5917",
      "baseVol": "66769.2785",
      "bidSz": "11.6597",
      "buyOne": "2917",
      "change": "0.00801",
      "changeUtc": "-0.01436",
      "close": "2917",
      "high24h": "2984.39",
      "low24h": "2857.14",
      "openUtc0": "2959.5",
      "quoteVol": "195195347.9561",
      "sellOne": "2917.01",
      "symbol": "ETHUSDT",
      "ts": "1764155653983",
      "usdtVol": "195195347.956051"
    },
    {
      "askSz": "23.1569",
      "baseVol": "480412.6382",
      "bidSz": "61.7539",
      "buyOne": "137.24",
      "change": "0.00823",
      "changeUtc": "-0.01223",
      "close": "137.27",
      "high24h": "140.66",
      "low24h": "133.13",
      "openUtc0": "138.97",
      "quoteVol": "65856421.3478",
      "sellOne": "137.25",
      "symbol": "SOLUSDT",
      "ts": "1764155653985",
      "usdtVol": "65856421.347792"
    },
    {
      "askSz": "47996.53",
      "baseVol": "16833337.92",
      "bidSz": "883.6",
      "buyOne": "0.2526",
      "change": "0.05909",
      "changeUtc": "0.04681",
      "close": "0.2527",
      "high24h": "0.2568",
      "low24h": "0.2365",
      "openUtc0": "0.2414",
      "quoteVol": "4113508.88",
      "sellOne": "0.2527",
      "symbol": "PIUSDT",
      "ts": "1764155654058",
      "usdtVol": "4113508.875283"
    }
  ]
}
