{
  "timestamp": "2025-10-31T01:05:56Z",
  "data": [
    {
      "askSz": "1.800306",
      "baseVol": "3949.783716",
      "bidSz": "0.046663",
      "buyOne": "109529.75",
      "change": "-0.00749",
      "changeUtc": "0.01121",
      "close": "109529.75",
      "high24h": "111595.75",
      "low24h": "106294.12",
      "openUtc0": "108312.59",
      "quoteVol": "429588385.293257",
      "sellOne": "109529.76",
      "symbol": "BTCUSDT",
      "ts": "1761872754677",
      "usdtVol": "429588385.2932561"
    },
    {
      "askSz": "3.3739",
      "baseVol": "65452.7828",
      "bidSz": "2.5412",
      "buyOne": "3838.43",
      "change": "-0.01922",
      "changeUtc": "0.00861",
      "close": "3838.58",
      "high24h": "3950.16",
      "low24h": "3680.28",
      "openUtc0": "3805.8",
      "quoteVol": "250260550.8377",
      "sellOne": "3838.44",
      "symbol": "ETHUSDT",
      "ts": "1761872755297",
      "usdtVol": "250260550.837649"
    },
    {
      "askSz": "52.6142",
      "baseVol": "418708.6128",
      "bidSz": "0.5377",
      "buyOne": "185.95",
      "change": "-0.04016",
      "changeUtc": "0.00688",
      "close": "185.95",
      "high24h": "198.19",
      "low24h": "178.69",
      "openUtc0": "184.68",
      "quoteVol": "78616968.5302",
      "sellOne": "185.96",
      "symbol": "SOLUSDT",
      "ts": "1761872754678",
      "usdtVol": "78616968.530195"
    },
    {
      "askSz": "35171.92",
      "baseVol": "18796634.34",
      "bidSz": "2010.45",
      "buyOne": "0.2564",
      "change": "-0.02584",
      "changeUtc": "0.02396",
      "close": "0.2564",
      "high24h": "0.2663",
      "low24h": "0.2335",
      "openUtc0": "0.2504",
      "quoteVol": "4702230.22",
      "sellOne": "0.2565",
      "symbol": "PIUSDT",
      "ts": "1761872755363",
      "usdtVol": "4702230.21728"
    }
  ]
}
