{
  "timestamp": "2025-11-27T17:44:03Z",
  "data": [
    {
      "askSz": "0.13912",
      "baseVol": "5264.841407",
      "bidSz": "3.824305",
      "buyOne": "91409.91",
      "change": "0.02136",
      "changeUtc": "0.01026",
      "close": "91409.91",
      "high24h": "91926.09",
      "low24h": "89485.09",
      "openUtc0": "90482.01",
      "quoteVol": "478259186.401846",
      "sellOne": "91409.92",
      "symbol": "BTCUSDT",
      "ts": "1764265441612",
      "usdtVol": "478259186.40184505"
    },
    {
      "askSz": "1.7041",
      "baseVol": "53332.7024",
      "bidSz": "8.2103",
      "buyOne": "3015.31",
      "change": "0.00036",
      "changeUtc": "-0.0036",
      "close": "3015.3",
      "high24h": "3071.05",
      "low24h": "2985.92",
      "openUtc0": "3026.2",
      "quoteVol": "161245615.9384",
      "sellOne": "3015.32",
      "symbol": "ETHUSDT",
      "ts": "1764265441612",
      "usdtVol": "161245615.938333"
    },
    {
      "askSz": "87.4801",
      "baseVol": "442144.6037",
      "bidSz": "83.7451",
      "buyOne": "141.48",
      "change": "0.01187",
      "changeUtc": "-0.01056",
      "close": "141.48",
      "high24h": "144.7",
      "low24h": "139.81",
      "openUtc0": "142.99",
      "quoteVol": "63073066.4572",
      "sellOne": "141.49",
      "symbol": "SOLUSDT",
      "ts": "1764265441614",
      "usdtVol": "63073066.45714"
    },
    {
      "askSz": "856.72",
      "baseVol": "16280928.08",
      "bidSz": "36352.8",
      "buyOne": "0.2739",
      "change": "0.07789",
      "changeUtc": "0.07578",
      "close": "0.274",
      "high24h": "0.2762",
      "low24h": "0.2511",
      "openUtc0": "0.2547",
      "quoteVol": "4238648.32",
      "sellOne": "0.2741",
      "symbol": "PIUSDT",
      "ts": "1764265442245",
      "usdtVol": "4238648.312332"
    }
  ]
}
