{
  "timestamp": "2025-11-23T09:53:42Z",
  "data": [
    {
      "askSz": "0.370622",
      "baseVol": "5720.057877",
      "bidSz": "1.74463",
      "buyOne": "86329.82",
      "change": "0.02753",
      "changeUtc": "0.01881",
      "close": "86329.82",
      "high24h": "86859.96",
      "low24h": "83500.38",
      "openUtc0": "84736.12",
      "quoteVol": "486631093.310514",
      "sellOne": "86329.83",
      "symbol": "BTCUSDT",
      "ts": "1763891621930",
      "usdtVol": "486631093.31051321"
    },
    {
      "askSz": "0.0483",
      "baseVol": "52417.9423",
      "bidSz": "11.0934",
      "buyOne": "2815.99",
      "change": "0.03115",
      "changeUtc": "0.01647",
      "close": "2815.99",
      "high24h": "2852.53",
      "low24h": "2704.3",
      "openUtc0": "2770.35",
      "quoteVol": "145738631.2044",
      "sellOne": "2816",
      "symbol": "ETHUSDT",
      "ts": "1763891621931",
      "usdtVol": "145738631.204389"
    },
    {
      "askSz": "196.9544",
      "baseVol": "369304.7285",
      "bidSz": "663.4362",
      "buyOne": "130.09",
      "change": "0.02708",
      "changeUtc": "0.01959",
      "close": "130.09",
      "high24h": "131.91",
      "low24h": "125.1",
      "openUtc0": "127.59",
      "quoteVol": "47405945.3446",
      "sellOne": "130.1",
      "symbol": "SOLUSDT",
      "ts": "1763891621931",
      "usdtVol": "47405945.344512"
    },
    {
      "askSz": "2703.37",
      "baseVol": "8573313.04",
      "bidSz": "5667.06",
      "buyOne": "0.239",
      "change": "0.00084",
      "changeUtc": "-0.00334",
      "close": "0.2391",
      "high24h": "0.2426",
      "low24h": "0.2367",
      "openUtc0": "0.2398",
      "quoteVol": "2056109.31",
      "sellOne": "0.2391",
      "symbol": "PIUSDT",
      "ts": "1763891621993",
      "usdtVol": "2056109.30506"
    }
  ]
}
