{
  "timestamp": "2025-11-27T08:59:49Z",
  "data": [
    {
      "askSz": "2.566831",
      "baseVol": "5661.46335",
      "bidSz": "0.538313",
      "buyOne": "91462.64",
      "change": "0.04629",
      "changeUtc": "0.01084",
      "close": "91462.65",
      "high24h": "91888.01",
      "low24h": "86306.69",
      "openUtc0": "90482.01",
      "quoteVol": "505956573.108754",
      "sellOne": "91462.65",
      "symbol": "BTCUSDT",
      "ts": "1764233988812",
      "usdtVol": "505956573.10875384"
    },
    {
      "askSz": "10.3599",
      "baseVol": "62704.5556",
      "bidSz": "1.0221",
      "buyOne": "3028.08",
      "change": "0.03954",
      "changeUtc": "0.00062",
      "close": "3028.08",
      "high24h": "3071.05",
      "low24h": "2888.5",
      "openUtc0": "3026.2",
      "quoteVol": "187271126.1398",
      "sellOne": "3028.09",
      "symbol": "ETHUSDT",
      "ts": "1764233988812",
      "usdtVol": "187271126.139792"
    },
    {
      "askSz": "45.1264",
      "baseVol": "604160.4948",
      "bidSz": "76.3656",
      "buyOne": "142.55",
      "change": "0.03357",
      "changeUtc": "-0.00301",
      "close": "142.56",
      "high24h": "144.7",
      "low24h": "135.52",
      "openUtc0": "142.99",
      "quoteVol": "84714411.328",
      "sellOne": "142.56",
      "symbol": "SOLUSDT",
      "ts": "1764233988812",
      "usdtVol": "84714411.327917"
    },
    {
      "askSz": "15166.58",
      "baseVol": "15939319.5",
      "bidSz": "2270.63",
      "buyOne": "0.2536",
      "change": "0.00595",
      "changeUtc": "-0.00432",
      "close": "0.2536",
      "high24h": "0.2593",
      "low24h": "0.2469",
      "openUtc0": "0.2547",
      "quoteVol": "4033726.98",
      "sellOne": "0.2537",
      "symbol": "PIUSDT",
      "ts": "1764233988873",
      "usdtVol": "4033726.974661"
    }
  ]
}
