{
  "timestamp": "2025-11-25T04:51:08Z",
  "data": [
    {
      "askSz": "0.728765",
      "baseVol": "8106.306286",
      "bidSz": "1.308906",
      "buyOne": "88318.67",
      "change": "0.01929",
      "changeUtc": "0.0004",
      "close": "88318.68",
      "high24h": "89212.7",
      "low24h": "85275.01",
      "openUtc0": "88283.43",
      "quoteVol": "707493485.301117",
      "sellOne": "88318.68",
      "symbol": "BTCUSDT",
      "ts": "1764046268336",
      "usdtVol": "707493485.30111654"
    },
    {
      "askSz": "2.7854",
      "baseVol": "91090.482",
      "bidSz": "4.5504",
      "buyOne": "2935.74",
      "change": "0.04049",
      "changeUtc": "-0.00603",
      "close": "2935.49",
      "high24h": "2985.98",
      "low24h": "2784.93",
      "openUtc0": "2953.29",
      "quoteVol": "262071112.429",
      "sellOne": "2935.75",
      "symbol": "ETHUSDT",
      "ts": "1764046268334",
      "usdtVol": "262071112.428904"
    },
    {
      "askSz": "23.4569",
      "baseVol": "656636.9709",
      "bidSz": "136.9137",
      "buyOne": "138.61",
      "change": "0.0564",
      "changeUtc": "0.0013",
      "close": "138.61",
      "high24h": "139.81",
      "low24h": "128.43",
      "openUtc0": "138.43",
      "quoteVol": "88178843.4626",
      "sellOne": "138.62",
      "symbol": "SOLUSDT",
      "ts": "1764046268335",
      "usdtVol": "88178843.462546"
    },
    {
      "askSz": "1480.86",
      "baseVol": "12034711.85",
      "bidSz": "4846.52",
      "buyOne": "0.2377",
      "change": "-0.01287",
      "changeUtc": "-0.00294",
      "close": "0.2378",
      "high24h": "0.2427",
      "low24h": "0.232",
      "openUtc0": "0.2385",
      "quoteVol": "2867677.6",
      "sellOne": "0.2378",
      "symbol": "PIUSDT",
      "ts": "1764046267175",
      "usdtVol": "2867677.592278"
    }
  ]
}
